{
  "lines": [
    {
      "ahb_expression": "Muss",
      "conditions": "",
      "data_element": "",
      "guid": "5985E2CB209E47E6751AA3D40AF702C8",
      "index": 0,
      "name": "",
      "section_name": "Nachrichten-Kopfsegment",
      "segment_code": "UNH",
      "segment_group_key": "",
      "value_pool_entry": "",
      "line_type": "segment"
    },
    {
      "ahb_expression": "X",
      "conditions": "",
      "data_element": "0062",
      "guid": "0D9B31FC3E055F0D702ED0E7AC9E850E",
      "index": 0,
      "name": "Nachrichten-Referenznummer",
      "section_name": "",
      "segment_code": "UNH",
      "segment_group_key": "",
      "value_pool_entry": "",
      "line_type": "dataelement"
    },
    {
      "ahb_expression": "X",
      "conditions": "",
      "data_element": "0065",
      "guid": "D45FF20D37906C88E670A574476A4D74",
      "index": 0,
      "name": "Bestellung",
      "section_name": "",
      "segment_code": "UNH",
      "segment_group_key": "",
      "value_pool_entry": "ORDERS",
      "line_type": "code"
    },
    {
      "ahb_expression": "X",
      "conditions": "",
      "data_element": "0052",
      "guid": "E2F798746E76D00C7A3CD3CEBC8F0A6A",
      "index": 0,
      "name": "Entwurfs-Version",
      "section_name": "",
      "segment_code": "UNH",
      "segment_group_key": "",
      "value_pool_entry": "D",
      "line_type": "code"
    },
    {
      "ahb_expression": "X",
      "conditions": "",
      "data_element": "0054",
      "guid": "2D0D9AC549E80C9CAC51D04866DF11E3",
      "index": 0,
      "name": "Ausgabe 2009 - B",
      "section_name": "",
      "segment_code": "UNH",
      "segment_group_key": "",
      "value_pool_entry": "09B",
      "line_type": "code"
    },
    {
      "ahb_expression": "X",
      "conditions": "",
      "data_element": "0051",
      "guid": "EDBF37066D69E8C09D862FB361F4DC54",
      "index": 0,
      "name": "UN/CEFACT",
      "section_name": "",
      "segment_code": "UNH",
      "segment_group_key": "",
      "value_pool_entry": "UN",
      "line_type": "code"
    },
    {
      "ahb_expression": "X",
      "conditions": "",
      "data_element": "0057",
      "guid": "4E40FFFFE83852E62065C064E445AFBC",
      "index": 0,
      "name": "Versionsnummer der zugrundeliegenden BDEW-Nachrichtenbeschreibung",
      "section_name": "",
      "segment_code": "UNH",
      "segment_group_key": "",
      "value_pool_entry": "1.4b",
      "line_type": "code"
    },
    {
      "ahb_expression": "Muss",
      "conditions": "",
      "data_element": "",
      "guid": "533B1DC5D3892D2E2C1E07BAD6CD6283",
      "index": 0,
      "name": "",
      "section_name": "Beginn der Nachricht",
      "segment_code": "BGM",
      "segment_group_key": "",
      "value_pool_entry": "",
      "line_type": "segment"
    },
    {
      "ahb_expression": "X",
      "conditions": "",
      "data_element": "1001",
      "guid": "40E7F5538D4BDD8F96628992EB3E79E4",
      "index": 0,
      "name": "Sperrung",
      "section_name": "",
      "segment_code": "BGM",
      "segment_group_key": "",
      "value_pool_entry": "Z51",
      "line_type": "code"
    },
    {
      "ahb_expression": "X",
      "conditions": "",
      "data_element": "1004",
      "guid": "69AE236FA24813AAA70D46E38F26D117",
      "index": 0,
      "name": "Dokumentennummer",
      "section_name": "",
      "segment_code": "BGM",
      "segment_group_key": "",
      "value_pool_entry": "",
      "line_type": "dataelement"
    },
    {
      "ahb_expression": "Muss",
      "conditions": "",
      "data_element": "",
      "guid": "7D1160221015554DD90D2F7016EE0DD7",
      "index": 0,
      "name": "",
      "section_name": "Nachrichtendatum",
      "segment_code": "DTM",
      "segment_group_key": "",
      "value_pool_entry": "",
      "line_type": "segment"
    },
    {
      "ahb_expression": "X",
      "conditions": "",
      "data_element": "2005",
      "guid": "064DB265A1F3A4A1D890E792DEF99D81",
      "index": 0,
      "name": "Dokumenten-/Nachrichtendatum/-zeit",
      "section_name": "",
      "segment_code": "DTM",
      "segment_group_key": "",
      "value_pool_entry": "137",
      "line_type": "code"
    },
    {
      "ahb_expression": "X [931] [494]",
      "conditions": "[494] Das hier genannte Datum muss der Zeitpunkt sein, zu dem das Dokument erstellt wurde, oder ein Zeitpunkt, der davor liegt.\n[931] Format: ZZZ = +00",
      "data_element": "2380",
      "guid": "6E648445D00E8695B8B422F192878BD0",
      "index": 0,
      "name": "Datum oder Uhrzeit oder Zeitspanne, Wert",
      "section_name": "",
      "segment_code": "DTM",
      "segment_group_key": "",
      "value_pool_entry": "",
      "line_type": "dataelement"
    },
    {
      "ahb_expression": "X",
      "conditions": "",
      "data_element": "2379",
      "guid": "9FC7320FD93D8E30414738EA3B06E4E9",
      "index": 0,
      "name": "CCYYMMDDHHMMZZZ",
      "section_name": "",
      "segment_code": "DTM",
      "segment_group_key": "",
      "value_pool_entry": "303",
      "line_type": "code"
    },
    {
      "ahb_expression": "Muss",
      "conditions": "",
      "data_element": "",
      "guid": "3FAF87A809A6FF2773FB43A992D4BF16",
      "index": 0,
      "name": "",
      "section_name": "Ausführungsdatum",
      "segment_code": "DTM",
      "segment_group_key": "",
      "value_pool_entry": "",
      "line_type": "segment"
    },
    {
      "ahb_expression": "X",
      "conditions": "",
      "data_element": "2005",
      "guid": "05F406BCBA170D1F9812E8E1EA82CC31",
      "index": 0,
      "name": "Ausführungsdatum/-zeit",
      "section_name": "",
      "segment_code": "DTM",
      "segment_group_key": "",
      "value_pool_entry": "203",
      "line_type": "code"
    },
    {
      "ahb_expression": "X [931]",
      "conditions": "[931] Format: ZZZ = +00",
      "data_element": "2380",
      "guid": "AA35E86651A3741AB11E06ED84DC4C4B",
      "index": 0,
      "name": "Datum oder Uhrzeit oder Zeitspanne, Wert",
      "section_name": "",
      "segment_code": "DTM",
      "segment_group_key": "",
      "value_pool_entry": "",
      "line_type": "dataelement"
    },
    {
      "ahb_expression": "X",
      "conditions": "",
      "data_element": "2379",
      "guid": "16C4688D2081250DCF95384C4CFEE60B",
      "index": 0,
      "name": "CCYYMMDDHHMMZZZ",
      "section_name": "",
      "segment_code": "DTM",
      "segment_group_key": "",
      "value_pool_entry": "303",
      "line_type": "code"
    },
    {
      "ahb_expression": "Muss",
      "conditions": "",
      "data_element": "",
      "guid": "271888100D4A39C127E0B1A3FC2DA0B9",
      "index": 0,
      "name": "",
      "section_name": "Prüfidentifikator",
      "segment_code": "",
      "segment_group_key": "SG1",
      "value_pool_entry": "",
      "line_type": "segment_group"
    },
    {
      "ahb_expression": "Muss",
      "conditions": "",
      "data_element": "",
      "guid": "AC1FDF0C9FB0BE77B9702B794FF9030A",
      "index": 0,
      "name": "",
      "section_name": "Prüfidentifikator",
      "segment_code": "RFF",
      "segment_group_key": "SG1",
      "value_pool_entry": "",
      "line_type": "segment"
    },
    {
      "ahb_expression": "X",
      "conditions": "",
      "data_element": "1153",
      "guid": "08B6687E3003B6A3E36C27DCBFCCECFC",
      "index": 0,
      "name": "Prüfidentifikator",
      "section_name": "",
      "segment_code": "RFF",
      "segment_group_key": "SG1",
      "value_pool_entry": "Z13",
      "line_type": "code"
    },
    {
      "ahb_expression": "X",
      "conditions": "",
      "data_element": "1154",
      "guid": "8D28D588854A589D7DBE9249356E772F",
      "index": 0,
      "name": "Anfrage Sperrung",
      "section_name": "",
      "segment_code": "RFF",
      "segment_group_key": "SG1",
      "value_pool_entry": "17116",
      "line_type": "code"
    },
    {
      "ahb_expression": "Muss",
      "conditions": "",
      "data_element": "",
      "guid": "A9709EEDF898A4A2E7515768A8BA3B34",
      "index": 0,
      "name": "",
      "section_name": "MP-ID Absender",
      "segment_code": "",
      "segment_group_key": "SG2",
      "value_pool_entry": "",
      "line_type": "segment_group"
    },
    {
      "ahb_expression": "Muss",
      "conditions": "",
      "data_element": "",
      "guid": "1E61CF83F44023D4F569F8A84BA5537A",
      "index": 0,
      "name": "",
      "section_name": "MP-ID Absender",
      "segment_code": "NAD",
      "segment_group_key": "SG2",
      "value_pool_entry": "",
      "line_type": "segment"
    },
    {
      "ahb_expression": "X",
      "conditions": "",
      "data_element": "3035",
      "guid": "C81579B577215AC103A94C8A416BF1ED",
      "index": 0,
      "name": "Dokumenten-/Nachrichtenaussteller bzw. -absender",
      "section_name": "",
      "segment_code": "NAD",
      "segment_group_key": "SG2",
      "value_pool_entry": "MS",
      "line_type": "code"
    },
    {
      "ahb_expression": "X",
      "conditions": "",
      "data_element": "3039",
      "guid": "3857C4D5FC99792E8E8185126A47F285",
      "index": 0,
      "name": "MP-ID",
      "section_name": "",
      "segment_code": "NAD",
      "segment_group_key": "SG2",
      "value_pool_entry": "",
      "line_type": "dataelement"
    },
    {
      "ahb_expression": "X",
      "conditions": "",
      "data_element": "3055",
      "guid": "5F45264182D7ACE744E6278BF8BA3AB6",
      "index": 0,
      "name": "GS1",
      "section_name": "",
      "segment_code": "NAD",
      "segment_group_key": "SG2",
      "value_pool_entry": "9",
      "line_type": "code"
    },
    {
      "ahb_expression": "X",
      "conditions": "",
      "data_element": "3055",
      "guid": "C62A89D867E6EDD8B1D66F528E2131B4",
      "index": 0,
      "name": "DE, BDEW (Bundesverband der Energie- und Wasserwirtschaft e.V.)",
      "section_name": "",
      "segment_code": "NAD",
      "segment_group_key": "SG2",
      "value_pool_entry": "293",
      "line_type": "code"
    },
    {
      "ahb_expression": "X",
      "conditions": "",
      "data_element": "3055",
      "guid": "60FB46D3950E5C7F2FF7945D1CF1DF5D",
      "index": 0,
      "name": "DE, DVGW Service & Consult GmbH",
      "section_name": "",
      "segment_code": "NAD",
      "segment_group_key": "SG2",
      "value_pool_entry": "332",
      "line_type": "code"
    },
    {
      "ahb_expression": "Muss",
      "conditions": "",
      "data_element": "",
      "guid": "757E7F7EA9AD9480EAA05A87FBD2B699",
      "index": 0,
      "name": "",
      "section_name": "Kontaktinformationen",
      "segment_code": "",
      "segment_group_key": "SG5",
      "value_pool_entry": "",
      "line_type": "segment_group"
    },
    {
      "ahb_expression": "Muss",
      "conditions": "",
      "data_element": "",
      "guid": "BFEFE9CD4EA352C87E2A56B176CB0AAB",
      "index": 0,
      "name": "",
      "section_name": "Ansprechpartner",
      "segment_code": "CTA",
      "segment_group_key": "SG5",
      "value_pool_entry": "",
      "line_type": "segment"
    },
    {
      "ahb_expression": "X",
      "conditions": "",
      "data_element": "3139",
      "guid": "E23A1D751B213ED826064896F91BE790",
      "index": 0,
      "name": "Informationskontakt",
      "section_name": "",
      "segment_code": "CTA",
      "segment_group_key": "SG5",
      "value_pool_entry": "IC",
      "line_type": "code"
    },
    {
      "ahb_expression": "X",
      "conditions": "",
      "data_element": "3412",
      "guid": "0FED7BEB81386E66ABC95ED2B79C21EC",
      "index": 0,
      "name": "Kontakt",
      "section_name": "",
      "segment_code": "CTA",
      "segment_group_key": "SG5",
      "value_pool_entry": "",
      "line_type": "dataelement"
    },
    {
      "ahb_expression": "Muss",
      "conditions": "",
      "data_element": "",
      "guid": "1682C7DE06931CD09D761EC48C7350BC",
      "index": 0,
      "name": "",
      "section_name": "Kommunikationsverbindung",
      "segment_code": "COM",
      "segment_group_key": "SG5",
      "value_pool_entry": "",
      "line_type": "segment"
    },
    {
      "ahb_expression": "X (([939] [147]) ∨ ([940] [148])) ∧ [567]",
      "conditions": "[147] wenn im DE3155 in demselben COM der Code EM vorhanden ist\n[148] wenn im DE3155 in demselben COM der Code TE / FX / AJ / AL vorhanden ist\n[567] Hinweis: Es darf nur eine Information im DE3148 übermittelt werden\n[939] Format: Die Zeichenkette muss die Zeichen @ und . enthalten\n[940] Format: Die Zeichenkette muss mit dem Zeichen + beginnen und danach dürfen nur noch Ziffern folgen",
      "data_element": "3148",
      "guid": "68975EB08FD5596686EE201876B4BC12",
      "index": 0,
      "name": "Kommunikationsadresse, Identifikation",
      "section_name": "",
      "segment_code": "COM",
      "segment_group_key": "SG5",
      "value_pool_entry": "",
      "line_type": "dataelement"
    },
    {
      "ahb_expression": "X [1P0..1]",
      "conditions": "[1P] --",
      "data_element": "3155",
      "guid": "A6AD603D80DE1838A797C312669E941B",
      "index": 0,
      "name": "Elektronische Post",
      "section_name": "",
      "segment_code": "COM",
      "segment_group_key": "SG5",
      "value_pool_entry": "EM",
      "line_type": "code"
    },
    {
      "ahb_expression": "X [1P0..1]",
      "conditions": "[1P] --",
      "data_element": "3155",
      "guid": "42C231BD27E673DE6F2A2D7CE240E3AB",
      "index": 0,
      "name": "Telefax",
      "section_name": "",
      "segment_code": "COM",
      "segment_group_key": "SG5",
      "value_pool_entry": "FX",
      "line_type": "code"
    },
    {
      "ahb_expression": "X [1P0..1]",
      "conditions": "[1P] --",
      "data_element": "3155",
      "guid": "76B929FF4870B36F862300A57A45480B",
      "index": 0,
      "name": "Telefon",
      "section_name": "",
      "segment_code": "COM",
      "segment_group_key": "SG5",
      "value_pool_entry": "TE",
      "line_type": "code"
    },
    {
      "ahb_expression": "X [1P0..1]",
      "conditions": "[1P] --",
      "data_element": "3155",
      "guid": "AAD206FFBC999E3AAE5CDC4F225211F9",
      "index": 0,
      "name": "weiteres Telefon",
      "section_name": "",
      "segment_code": "COM",
      "segment_group_key": "SG5",
      "value_pool_entry": "AJ",
      "line_type": "code"
    },
    {
      "ahb_expression": "X [1P0..1]",
      "conditions": "[1P] --",
      "data_element": "3155",
      "guid": "26AE70E9A344709F95262216BEFE45EF",
      "index": 0,
      "name": "Handy",
      "section_name": "",
      "segment_code": "COM",
      "segment_group_key": "SG5",
      "value_pool_entry": "AL",
      "line_type": "code"
    },
    {
      "ahb_expression": "Muss",
      "conditions": "",
      "data_element": "",
      "guid": "597208CC59761D7660CAEF704978099F",
      "index": 0,
      "name": "",
      "section_name": "MP-ID Empfänger",
      "segment_code": "",
      "segment_group_key": "SG2",
      "value_pool_entry": "",
      "line_type": "segment_group"
    },
    {
      "ahb_expression": "Muss",
      "conditions": "",
      "data_element": "",
      "guid": "409AA48DBCEDD2780B992AE5E6DC7833",
      "index": 0,
      "name": "",
      "section_name": "MP-ID Empfänger",
      "segment_code": "NAD",
      "segment_group_key": "SG2",
      "value_pool_entry": "",
      "line_type": "segment"
    },
    {
      "ahb_expression": "X",
      "conditions": "",
      "data_element": "3035",
      "guid": "D6D8C18730E053D29E7694BF656222D9",
      "index": 0,
      "name": "Nachrichtenempfänger",
      "section_name": "",
      "segment_code": "NAD",
      "segment_group_key": "SG2",
      "value_pool_entry": "MR",
      "line_type": "code"
    },
    {
      "ahb_expression": "X",
      "conditions": "",
      "data_element": "3039",
      "guid": "56B6E3F1854EBE3FDEB661A40DD6C818",
      "index": 0,
      "name": "MP-ID",
      "section_name": "",
      "segment_code": "NAD",
      "segment_group_key": "SG2",
      "value_pool_entry": "",
      "line_type": "dataelement"
    },
    {
      "ahb_expression": "X",
      "conditions": "",
      "data_element": "3055",
      "guid": "7BE133351C05E3A22CD9A1BB27027C81",
      "index": 0,
      "name": "GS1",
      "section_name": "",
      "segment_code": "NAD",
      "segment_group_key": "SG2",
      "value_pool_entry": "9",
      "line_type": "code"
    },
    {
      "ahb_expression": "X",
      "conditions": "",
      "data_element": "3055",
      "guid": "D322D5DE91C86E55D962D8E826C0AFE3",
      "index": 0,
      "name": "DE, BDEW (Bundesverband der Energie- und Wasserwirtschaft e.V.)",
      "section_name": "",
      "segment_code": "NAD",
      "segment_group_key": "SG2",
      "value_pool_entry": "293",
      "line_type": "code"
    },
    {
      "ahb_expression": "X",
      "conditions": "",
      "data_element": "3055",
      "guid": "46ACDDE22562C436D1AC616C4FC4D4DF",
      "index": 0,
      "name": "DE, DVGW Service & Consult GmbH",
      "section_name": "",
      "segment_code": "NAD",
      "segment_group_key": "SG2",
      "value_pool_entry": "332",
      "line_type": "code"
    },
    {
      "ahb_expression": "Muss",
      "conditions": "",
      "data_element": "",
      "guid": "A9F181322987A7F87DF3C7EABEDCC568",
      "index": 0,
      "name": "",
      "section_name": "Marktlokation, Messlokation, Tranche bzw. Ressource",
      "segment_code": "",
      "segment_group_key": "SG2",
      "value_pool_entry": "",
      "line_type": "segment_group"
    },
    {
      "ahb_expression": "Muss",
      "conditions": "",
      "data_element": "",
      "guid": "D06FD7193FD751EFA49E944BC43F2ED5",
      "index": 0,
      "name": "",
      "section_name": "Meldepunkt",
      "segment_code": "NAD",
      "segment_group_key": "SG2",
      "value_pool_entry": "",
      "line_type": "segment"
    },
    {
      "ahb_expression": "X",
      "conditions": "",
      "data_element": "3035",
      "guid": "8365E1E7EEDE956F95ED097DAB199D41",
      "index": 0,
      "name": "Lieferanschrift",
      "section_name": "",
      "segment_code": "NAD",
      "segment_group_key": "SG2",
      "value_pool_entry": "DP",
      "line_type": "code"
    },
    {
      "ahb_expression": "Muss",
      "conditions": "",
      "data_element": "",
      "guid": "41E892DA1CD1FE0FDC028E29DCABF6C0",
      "index": 0,
      "name": "",
      "section_name": "Meldepunkt",
      "segment_code": "LOC",
      "segment_group_key": "SG2",
      "value_pool_entry": "",
      "line_type": "segment"
    },
    {
      "ahb_expression": "X",
      "conditions": "",
      "data_element": "3227",
      "guid": "A183BBE59C6ABD0AE1801306CA2C3EE2",
      "index": 0,
      "name": "Meldepunkt",
      "section_name": "",
      "segment_code": "LOC",
      "segment_group_key": "SG2",
      "value_pool_entry": "172",
      "line_type": "code"
    },
    {
      "ahb_expression": "X [950] [521]",
      "conditions": "[521] Hinweis: Verwendung der ID der Marktlokation\n[950] Format: Marktlokations-ID",
      "data_element": "3225",
      "guid": "64A4821F2E902607BACFF8CCD3E27230",
      "index": 0,
      "name": "Identifikator",
      "section_name": "",
      "segment_code": "LOC",
      "segment_group_key": "SG2",
      "value_pool_entry": "",
      "line_type": "dataelement"
    },
    {
      "ahb_expression": "Kann",
      "conditions": "",
      "data_element": "",
      "guid": "759851A7791EA54459791048B41ED572",
      "index": 0,
      "name": "",
      "section_name": "Adresse für Treffpunkt",
      "segment_code": "",
      "segment_group_key": "SG2",
      "value_pool_entry": "",
      "line_type": "segment_group"
    },
    {
      "ahb_expression": "Muss",
      "conditions": "",
      "data_element": "",
      "guid": "C9A16E11784CD9E9FEDF2DFE4D9FF8AA",
      "index": 0,
      "name": "",
      "section_name": "Adresse für Treffpunkt",
      "segment_code": "NAD",
      "segment_group_key": "SG2",
      "value_pool_entry": "",
      "line_type": "segment"
    },
    {
      "ahb_expression": "X",
      "conditions": "",
      "data_element": "3035",
      "guid": "1866FF078BA5479209ADFCE38F2F8973",
      "index": 0,
      "name": "Treffpunkt",
      "section_name": "",
      "segment_code": "NAD",
      "segment_group_key": "SG2",
      "value_pool_entry": "Z24",
      "line_type": "code"
    },
    {
      "ahb_expression": "K",
      "conditions": "",
      "data_element": "3124",
      "guid": "3843721E5DF3C034B708C35484BDF60C",
      "index": 0,
      "name": "Zusatzinformation zur Identifizierung",
      "section_name": "",
      "segment_code": "NAD",
      "segment_group_key": "SG2",
      "value_pool_entry": "",
      "line_type": "dataelement"
    },
    {
      "ahb_expression": "M [57]",
      "conditions": "[57] Wenn im selben SG2 NAD DE3124 nicht vorhanden",
      "data_element": "3042",
      "guid": "1D5C291810AC44C1B7CBC6A899E28E0B",
      "index": 0,
      "name": "Straße und Hausnummer oder Postfach",
      "section_name": "",
      "segment_code": "NAD",
      "segment_group_key": "SG2",
      "value_pool_entry": "",
      "line_type": "dataelement"
    },
    {
      "ahb_expression": "X",
      "conditions": "",
      "data_element": "3164",
      "guid": "9155A145BE0D0A7877FF5960D6F726B4",
      "index": 0,
      "name": "Ort",
      "section_name": "",
      "segment_code": "NAD",
      "segment_group_key": "SG2",
      "value_pool_entry": "",
      "line_type": "dataelement"
    },
    {
      "ahb_expression": "X",
      "conditions": "",
      "data_element": "3251",
      "guid": "7386FDFC7E4214431FBA66541DB0C47D",
      "index": 0,
      "name": "Postleitzahl, Code",
      "section_name": "",
      "segment_code": "NAD",
      "segment_group_key": "SG2",
      "value_pool_entry": "",
      "line_type": "dataelement"
    },
    {
      "ahb_expression": "X",
      "conditions": "",
      "data_element": "3207",
      "guid": "F01DDFCCB38BA04ED34C8AB566F4D4B0",
      "index": 0,
      "name": "Ländername, Code",
      "section_name": "",
      "segment_code": "NAD",
      "segment_group_key": "SG2",
      "value_pool_entry": "",
      "line_type": "dataelement"
    },
    {
      "ahb_expression": "Kann [2092]",
      "conditions": "[2092] Pro Nachricht ist die SG29 maximal einmal anzugeben",
      "data_element": "",
      "guid": "BF51F3914877F9715C306AD8326C1246",
      "index": 0,
      "name": "",
      "section_name": "Positionsteil",
      "segment_code": "",
      "segment_group_key": "SG29",
      "value_pool_entry": "",
      "line_type": "segment_group"
    },
    {
      "ahb_expression": "Muss",
      "conditions": "",
      "data_element": "",
      "guid": "FC2D416EEE1493E2BBB3BFB26186F217",
      "index": 0,
      "name": "",
      "section_name": "Positionsdaten",
      "segment_code": "LIN",
      "segment_group_key": "SG29",
      "value_pool_entry": "",
      "line_type": "segment"
    },
    {
      "ahb_expression": "X [903]",
      "conditions": "[903] Format: Möglicher Wert: 1",
      "data_element": "1082",
      "guid": "DCE29B8F156A69EC14067F3829C3CD43",
      "index": 0,
      "name": "Positionsnummer",
      "section_name": "",
      "segment_code": "LIN",
      "segment_group_key": "SG29",
      "value_pool_entry": "",
      "line_type": "dataelement"
    },
    {
      "ahb_expression": "Kann",
      "conditions": "",
      "data_element": "",
      "guid": "2659B4D8136FDDECE3A215419055E045",
      "index": 0,
      "name": "",
      "section_name": "Allgemeine Information (Feld für allgemeine Hinweise)",
      "segment_code": "FTX",
      "segment_group_key": "SG29",
      "value_pool_entry": "",
      "line_type": "segment"
    },
    {
      "ahb_expression": "X",
      "conditions": "",
      "data_element": "4451",
      "guid": "033C23437768278A5EB06459ABC4BBA5",
      "index": 0,
      "name": "Zusätzliche Informationen (für allgemeine Hinweise)",
      "section_name": "",
      "segment_code": "FTX",
      "segment_group_key": "SG29",
      "value_pool_entry": "ACB",
      "line_type": "code"
    },
    {
      "ahb_expression": "X",
      "conditions": "",
      "data_element": "4440",
      "guid": "1B1D1158334E387A832F348EDDC5F59C",
      "index": 0,
      "name": "Freier Text",
      "section_name": "",
      "segment_code": "FTX",
      "segment_group_key": "SG29",
      "value_pool_entry": "",
      "line_type": "dataelement"
    },
    {
      "ahb_expression": "Muss",
      "conditions": "",
      "data_element": "",
      "guid": "9A085ADFA9A2E19413F5F8B7E268F561",
      "index": 0,
      "name": "",
      "section_name": "Abschnitts-Kontrollsegment",
      "segment_code": "UNS",
      "segment_group_key": "",
      "value_pool_entry": "",
      "line_type": "segment"
    },
    {
      "ahb_expression": "X",
      "conditions": "",
      "data_element": "0081",
      "guid": "A19FE891D7982213869DFD95D34FD66F",
      "index": 0,
      "name": "Trennung von Positions- und Summenteil",
      "section_name": "",
      "segment_code": "UNS",
      "segment_group_key": "",
      "value_pool_entry": "S",
      "line_type": "code"
    },
    {
      "ahb_expression": "Muss",
      "conditions": "",
      "data_element": "",
      "guid": "51FBB6E131F316317DB813E9A130B5ED",
      "index": 0,
      "name": "",
      "section_name": "Nachrichten-Endesegment",
      "segment_code": "UNT",
      "segment_group_key": "",
      "value_pool_entry": "",
      "line_type": "segment"
    },
    {
      "ahb_expression": "X",
      "conditions": "",
      "data_element": "0074",
      "guid": "B0FAD01B837CC3F67209F6D97CCCEDF9",
      "index": 0,
      "name": "Anzahl der Segmente in einer Nachricht",
      "section_name": "",
      "segment_code": "UNT",
      "segment_group_key": "",
      "value_pool_entry": "",
      "line_type": "dataelement"
    },
    {
      "ahb_expression": "X",
      "conditions": "",
      "data_element": "0062",
      "guid": "07F081CBCF0FECAFB16D530009AF96A3",
      "index": 0,
      "name": "Nachrichten-Referenznummer",
      "section_name": "",
      "segment_code": "UNT",
      "segment_group_key": "",
      "value_pool_entry": "",
      "line_type": "dataelement"
    }
  ],
  "meta": {
    "description": "Anfrage Sperrung",
    "direction": "NB → MSB",
    "pruefidentifikator": "17116",
    "versionsnummer": "1.1a",
    "veroeffentlichungsdatum": "2025-10-01"
  }
}